floggerx/FloggerX.py
floggerx/__init__.py
floggerx-1.0.0.dist-info/licenses/LICENSE
floggerx-1.0.0.dist-info/METADATA
floggerx-1.0.0.dist-info/WHEEL
floggerx-1.0.0.dist-info/top_level.txt
floggerx-1.0.0.dist-info/RECORD
