Metadata-Version: 2.4
Name: floggerX
Version: 1.0.0
Summary: A flexible logging utility for your Python projects
Author: Futuregus
License-Expression: MIT
Project-URL: Homepage, https://github.com/Futuregus/Flogger
License-File: LICENSE
Dynamic: license-file
